MANIFEST.in
README.md
setup.cfg
setup.py
aiodnsbrute/__init__.py
aiodnsbrute/cli.py
aiodnsbrute/logger.py
aiodnsbrute.egg-info/PKG-INFO
aiodnsbrute.egg-info/SOURCES.txt
aiodnsbrute.egg-info/dependency_links.txt
aiodnsbrute.egg-info/entry_points.txt
aiodnsbrute.egg-info/not-zip-safe
aiodnsbrute.egg-info/requires.txt
aiodnsbrute.egg-info/top_level.txt
aiodnsbrute/wordlists/bitquark_20160227_subdomains_popular_1000
aiodnsbrute/wordlists/bitquark_20160227_subdomains_popular_10000
aiodnsbrute/wordlists/bitquark_20160227_subdomains_popular_100000
aiodnsbrute/wordlists/bitquark_20160227_subdomains_popular_1000000
aiodnsbrute/wordlists/names_large.txt
aiodnsbrute/wordlists/top10m.7z